subdomain_permut/__init__.py
subdomain_permut/__version__.py
subdomain_permut/keywords.py
subdomain_permut/main.py
subdomain_permut/permut_methods.py
subdomain_permut/utility.py
subdomain_permut-0.0.8.dist-info/licenses/LICENSE
subdomain_permut-0.0.8.dist-info/METADATA
subdomain_permut-0.0.8.dist-info/WHEEL
subdomain_permut-0.0.8.dist-info/entry_points.txt
subdomain_permut-0.0.8.dist-info/top_level.txt
subdomain_permut-0.0.8.dist-info/RECORD
