Metadata-Version: 2.4
Name: subdomain-permut
Version: 0.0.8
Summary: A tool for generating subdomain permutations
Home-page: https://github.com/shriyanss/subdomain-permut
Author: Shriyans Sudhi
Author-email: shriyanss@ss0x00.com
Classifier: Programming Language :: Python :: 3
Classifier: License :: OSI Approved :: MIT License
Classifier: Operating System :: OS Independent
Requires-Python: >=3.6
License-File: LICENSE
Requires-Dist: psutil
Requires-Dist: tqdm
Dynamic: author
Dynamic: author-email
Dynamic: classifier
Dynamic: description
Dynamic: description-content-type
Dynamic: home-page
Dynamic: license-file
Dynamic: requires-dist
Dynamic: requires-python
Dynamic: summary
